{
  "skippableComposables": 93,
  "restartableComposables": 133,
  "readonlyComposables": 0,
  "totalComposables": 139,
  "restartGroups": 133,
  "totalGroups": 164,
  "staticArguments": 275,
  "certainArguments": 39,
  "knownStableArguments": 1619,
  "knownUnstableArguments": 27,
  "unknownStableArguments": 15,
  "totalArguments": 1661,
  "markedStableClasses": 1,
  "inferredStableClasses": 20,
  "inferredUnstableClasses": 38,
  "inferredUncertainClasses": 3,
  "effectivelyStableClasses": 21,
  "totalClasses": 62,
  "memoizedLambdas": 140,
  "singletonLambdas": 0,
  "singletonComposableLambdas": 23,
  "composableLambdas": 69,
  "totalLambdas": 140,
  "featureFlags": {
    "StrongSkipping": true,
    "IntrinsicRemember": true,
    "OptimizeNonSkippingGroups": false,
    "PausableComposition": false
  }
}